jumperpy/__init__.py
jumperpy/db.py
jumperpy/helper.py
jumperpy/kms.py
jumperpy/kms_helper.py
jumperpy/login.py
jumperpy-0.0.3.dist-info/LICENSE
jumperpy-0.0.3.dist-info/METADATA
jumperpy-0.0.3.dist-info/WHEEL
jumperpy-0.0.3.dist-info/top_level.txt
jumperpy-0.0.3.dist-info/RECORD
