Metadata-Version: 2.1
Name: jumperpy
Version: 0.0.3
Summary: Jumper-python micro framework for App Engine
Home-page: https://github.com/pypa/sampleproject
Author: Hal Jordan
Author-email: hal.jordan.py@gmail.com
License: UNKNOWN
Platform: UNKNOWN
Classifier: Programming Language :: Python :: 3
Classifier: License :: OSI Approved :: MIT License
Classifier: Operating System :: OS Independent
Requires-Python: >=3.6
